setup.py
PyCodeX.egg-info/PKG-INFO
PyCodeX.egg-info/SOURCES.txt
PyCodeX.egg-info/dependency_links.txt
PyCodeX.egg-info/requires.txt
PyCodeX.egg-info/top_level.txt
codex/__init__.py
codex/tornado/__init__.py
codex/tornado/database.py
codex/tornado/datetime.py
codex/tornado/helpers.py
codex/tornado/session.py
codex/tornado/template.py
codex/tornado/form/__init__.py
codex/tornado/form/rules.py