Metadata-Version: 1.0
Name: PyCodeX
Version: 0.0.3
Summary: CodeX Python Libraries
Home-page: https://github.com/tontonskie/pycodex
Author: Anthony De Leon
Author-email: tonton.dev001@gmail.com
License: UNKNOWN
Platform: UNKNOWN
